MANIFEST.in
README.md
setup.cfg
setup.py
versioneer.py
src/sqarf/__init__.py
src/sqarf/_version.py
src/sqarf/context.py
src/sqarf/exporter.py
src/sqarf/html_table_export.py
src/sqarf/html_tree_export.py
src/sqarf/log.py
src/sqarf/qatest.py
src/sqarf/session.py
src/sqarf.egg-info/PKG-INFO
src/sqarf.egg-info/SOURCES.txt
src/sqarf.egg-info/dependency_links.txt
src/sqarf.egg-info/requires.txt
src/sqarf.egg-info/top_level.txt