Metadata-Version: 2.1
Name: sqarf
Version: 1.0.0
Summary: Simple Quality Assurance Reports and Fixes
Home-page: https://gitlab.com/kabaretstudio/sqarf
Author: Damien "dee" Coureau
Author-email: dee909@gmail.com
License: LGPLv3+
Keywords: kabaret blender b3d pipeline dataflow workflow
Platform: UNKNOWN
Classifier: Development Status :: 4 - Beta
Classifier: Intended Audience :: Developers
Classifier: Operating System :: OS Independent
Classifier: Programming Language :: Python :: 2.7
Classifier: Programming Language :: Python :: 3.7
Classifier: License :: OSI Approved :: GNU Lesser General Public License v3 or later (LGPLv3+)
Provides-Extra: dev
